
{
	"NW": {
		"id": "41 205 254 41",
		"x": 199,
		"y": 198,
		"d": "s"
	},

	"NE": {
		"id": "252 94 249 41",
		"x": 1150,
		"y": 198,
		"d": "s"
	},

	"SE": {
		"id": "227 134 166 137",
		"x": 1152,
		"y": 758,
		"d": "n"
	},

	"SW": {
		"id": "47 34 231 89",
		"x": 199,
		"y": 758,
		"d": "e"
	},

	"UB": {
		"id": "57 156 167 137",
		"x": 666,
		"y": 478,
		"d": "e"
	},




	"N1": {
		"id": "140 88 228 137",
		"x": 317,
		"y": 198,
		"d": "w"
	},
	"N2": {
		"id": "158 220 186 89",
		"x": 435,
		"y": 198,
		"d": "w"
	},
	"N3": {
		"id": "220 24 232 137",
		"x": 553,
		"y": 198,
		"d": "w"
	},
	"N4": {
		"id": "119 44 171 169",
		"x": 666,
		"y": 198,
		"d": "e"
	},
	"N5": {
		"id": "193 125 198 89",
		"x": 789,
		"y": 198,
		"d": "e"
	},
	"N6": {
		"id": "014 137 254 41",
		"x": 907,
		"y": 198,
		"d": "e"
	},
	"N7": {
		"id": "81 127 227 137",
		"x": 1025,
		"y": 198,
		"d": "e"
	},




	"S1": {
		"id": "186 134 166 137",
		"x": 317,
		"y": 758,
		"d": "e"
	},
	"S2": {
		"id": "78 95 166 137",
		"x": 435,
		"y": 758,
		"d": "e"
	},
	"S3": {
		"id": "255 014 167 137",
		"x": 553,
		"y": 758,
		"d": "e"
	},
	"S4": {
		"id": "217 117 197 89",
		"x": 666,
		"y": 758,
		"d": "e"
	},
	"S5": {
		"id": "137 40 167 137",
		"x": 789,
		"y": 758,
		"d": "e"
	},
	"S6": {
		"id": "01 180 166 137",
		"x": 907,
		"y": 758,
		"d": "e"
	},
	"S7": {
		"id": "50 74 227 41",
		"x": 1025,
		"y": 758,
		"d": "e"
	},




	"W1": {
		"id": "27 06 231 89",
		"x": 199,
		"y": 312,
		"d": "s"
	},
	"W2": {
		"id": "01 84 254 41",
		"x": 199,
		"y": 422,
		"d": "s"
	},
	"W3": {
		"id": "86 013 231 89",
		"x": 199,
		"y": 532,
		"d": "s"
	},
	"W4": {
		"id": "187 205 166 137",
		"x": 199,
		"y": 642,
		"d": "s"
	},





	"E1": {
		"id": "x",
		"x": 1152,
		"y": 312,
		"d": "s"
	},
	"E2": {
		"id": "x",
		"x": 1152,
		"y": 422,
		"d": "s"
	},
	"E3": {
		"id": "x",
		"x": 1152,
		"y": 532,
		"d": "n"
	},
	"E4": {
		"id": "w",
		"x": 1152,
		"y": 642,
		"d": "n"
	},





	"B1": {
		"id": "243 223 166 137",
		"x": 317,
		"y": 478,
		"d": "w"
	},
	"B2": {
		"id": "43 180 230 89",
		"x": 435,
		"y": 478,
		"d": "w"
	},
	"B3": {
		"id": "206 93 226 41",
		"x": 553,
		"y": 478,
		"d": "w"
	},
	"B4": {
		"id": "218 125 230 89",
		"x": 666,
		"y": 478,
		"d": "w"
	},
	"B5": {
		"id": "95 173 230 89",
		"x": 789,
		"y": 478,
		"d": "w"
	},
	"B6": {
		"id": "128 03 231 89",
		"x": 907,
		"y": 478,
		"d": "w"
	},
	"B7": {
		"id": "250 68 255 41",
		"x": 1025,
		"y": 478,
		"d": "w"
	},




	"C1": {
		"id": "x",
		"x": 666,
		"y": 303,
		"d": "n"
	},
	"C2": {
		"id": "x",
		"x": 666,
		"y": 373,
		"d": "n"
	},
	"C3": {
		"id": "x",
		"x": 666,
		"y": 583,
		"d": "n"
	},
	"C4": {
		"id": "n",
		"x": 666,
		"y": 653,
		"d": "n"
	}
}